[
null,
{"id":1,"expanded":true,"name":"MAP001","order":1,"parentId":0,"scrollX":1126.2857142857142,"scrollY":636},
{"id":2,"expanded":true,"name":"Town 1","order":2,"parentId":1,"scrollX":1126.2857142857142,"scrollY":636},
{"id":3,"expanded":true,"name":"Inn","order":3,"parentId":2,"scrollX":1126.2857142857142,"scrollY":636},
{"id":4,"expanded":true,"name":"Josh's House Start","order":6,"parentId":1,"scrollX":898,"scrollY":302},
{"id":5,"expanded":true,"name":"Outside Josh's house","order":7,"parentId":4,"scrollX":534,"scrollY":314},
{"id":6,"expanded":true,"name":"Josh's House","order":9,"parentId":4,"scrollX":832,"scrollY":402.6666666666667},
{"id":7,"expanded":true,"name":"Pathway 1","order":10,"parentId":6,"scrollX":534,"scrollY":310},
{"id":8,"expanded":false,"name":"Outside Josh's house Start","order":8,"parentId":5,"scrollX":1126.2857142857142,"scrollY":636},
{"id":9,"expanded":true,"name":"Pathway 2","order":11,"parentId":7,"scrollX":534,"scrollY":314},
{"id":10,"expanded":true,"name":"DK Crew House","order":12,"parentId":9,"scrollX":709.3333333333334,"scrollY":450.6666666666667},
{"id":11,"expanded":true,"name":"DK House","order":13,"parentId":10,"scrollX":534,"scrollY":554},
{"id":12,"expanded":false,"name":"Shop","order":18,"parentId":1,"scrollX":1126.2857142857142,"scrollY":636},
{"id":13,"expanded":false,"name":"Test Dungeon","order":14,"parentId":11,"scrollX":709.3333333333334,"scrollY":904},
{"id":14,"expanded":false,"name":"Bar","order":4,"parentId":3,"scrollX":534,"scrollY":314},
{"id":15,"expanded":false,"name":"Shop 2","order":5,"parentId":2,"scrollX":1126.2857142857142,"scrollY":636},
{"id":16,"expanded":true,"name":"Basement 2","order":17,"parentId":4,"scrollX":709.3333333333334,"scrollY":402.6666666666667},
{"id":17,"expanded":false,"name":"Basement","order":16,"parentId":6,"scrollX":720,"scrollY":413.3333333333333},
{"id":18,"expanded":false,"name":"Basement 3","order":15,"parentId":6,"scrollX":720,"scrollY":413.3333333333333}
]